vspreview/__init__.py
vspreview/__main__.py
vspreview/_metadata.py
vspreview/init.py
vspreview/py.typed
vspreview/qt_patch.py
vspreview/api/__init__.py
vspreview/api/app.py
vspreview/api/info.py
vspreview/api/nodes.py
vspreview/api/other.py
vspreview/api/output.py
vspreview/core/__init__.py
vspreview/core/abstracts.py
vspreview/core/bases.py
vspreview/core/logger.py
vspreview/core/vsenv.py
vspreview/core/custom/__init__.py
vspreview/core/custom/combobox.py
vspreview/core/custom/dragnavigator.py
vspreview/core/custom/edits.py
vspreview/core/custom/graphicsview.py
vspreview/core/custom/misc.py
vspreview/core/custom/notch.py
vspreview/core/custom/plotting.py
vspreview/core/types/__init__.py
vspreview/core/types/audio.py
vspreview/core/types/misc.py
vspreview/core/types/scene.py
vspreview/core/types/units.py
vspreview/core/types/video.py
vspreview/core/types/yaml.py
vspreview/main/__init__.py
vspreview/main/dialog.py
vspreview/main/settings.py
vspreview/main/timeline.py
vspreview/main/window.py
vspreview/models/__init__.py
vspreview/models/generalmodel.py
vspreview/models/outputs.py
vspreview/models/scening.py
vspreview/plugins/__init__.py
vspreview/plugins/abstract.py
vspreview/plugins/install.py
vspreview/plugins/utils.py
vspreview/plugins/builtins/frame_props.ppy
vspreview/plugins/builtins/slowpics_comp.ppy
vspreview/plugins/builtins/split_view.ppy
vspreview/plugins/builtins/vssource_load.ppy
vspreview/plugins/builtins/frame_props/__init__.py
vspreview/plugins/builtins/frame_props/category.py
vspreview/plugins/builtins/frame_props/exclude.py
vspreview/plugins/builtins/frame_props/lut.py
vspreview/plugins/builtins/frame_props/py.typed
vspreview/plugins/builtins/slowpics_comp/__init__.py
vspreview/plugins/builtins/slowpics_comp/history.py
vspreview/plugins/builtins/slowpics_comp/main.py
vspreview/plugins/builtins/slowpics_comp/py.typed
vspreview/plugins/builtins/slowpics_comp/settings.py
vspreview/plugins/builtins/slowpics_comp/utils.py
vspreview-0.17.0.dist-info/METADATA
vspreview-0.17.0.dist-info/WHEEL
vspreview-0.17.0.dist-info/entry_points.txt
vspreview-0.17.0.dist-info/licenses/LICENSE
vspreview-0.17.0.dist-info/RECORD
