Metadata-Version: 2.4
Name: vspreview
Version: 0.17.0
Summary: VapourSynth Preview Tool
Project-URL: Source Code, https://github.com/Jaded-Encoding-Thaumaturgy/vs-preview
Project-URL: Contact, https://discord.gg/XTpc6Fa9eB
Author: Endilll
Maintainer-email: Setsugen no ao <setsugen@setsugen.dev>, Jaded Encoding Thaumaturgy <jaded.encoding.thaumaturgy@gmail.com>
License-Expression: Apache-2.0
License-File: LICENSE
Classifier: Development Status :: 4 - Beta
Classifier: License :: OSI Approved :: Apache Software License
Classifier: Natural Language :: English
Classifier: Operating System :: OS Independent
Classifier: Programming Language :: Python :: 3
Classifier: Programming Language :: Python :: 3 :: Only
Classifier: Topic :: Multimedia :: Graphics
Requires-Python: >=3.12
Requires-Dist: jetpytools~=1.7.0
Requires-Dist: matplotlib>=3.10.3
Requires-Dist: numpy>=2.3.1
Requires-Dist: pillow>=11.3.0; platform_system == 'Windows'
Requires-Dist: pyqt6-sip>=13.10.0
Requires-Dist: pyqt6>=6.9.0
Requires-Dist: pywin32>=307; platform_system == 'Windows'
Requires-Dist: pyyaml>=6.0.2
Requires-Dist: qdarkstyle>=3.2.3
Requires-Dist: requests-toolbelt>=1.0.0
Requires-Dist: requests>=2.31.0
Requires-Dist: vapoursynth>=68; platform_system == 'Windows'
Requires-Dist: vapoursynth>=70; platform_system != 'Windows'
Requires-Dist: vsengine>=0.2.0
Requires-Dist: vsjetpack>=0.7.0
